{
  "_class": "symbolInstance",
  "booleanOperation": 0,
  "clippingMaskMode": 0,
  "do_objectID": "042E1374-648F-43A0-AA97-2395BE9A4627",
  "exportOptions": {
    "_class": "exportOptions",
    "do_objectID": "269BEA69-13B3-4B02-AD1A-461BAF07BD8E",
    "exportFormats": [
    ],
    "includedLayerIds": [
    ],
    "layerOptions": 0,
    "shouldTrim": false
  },
  "frame": {
    "_class": "rect",
    "constrainProportions": false,
    "do_objectID": "59B22E81-3924-4B9B-B654-660F9ACE9512",
    "height": 21.16378348214289,
    "width": 20.67131696428567,
    "x": -0.1665736607143344,
    "y": -0.7181919642857792
  },
  "hasClippingMask": false,
  "horizontalSpacing": 0,
  "isFixedToViewport": false,
  "isFlippedHorizontal": false,
  "isFlippedVertical": false,
  "isLocked": false,
  "isVisible": true,
  "layerListExpandedType": 0,
  "name": "tint",
  "nameIsFixed": true,
  "overrideValues": [
  ],
  "resizingConstraint": 63,
  "resizingType": 0,
  "rotation": 0,
  "scale": 1,
  "shouldBreakMaskChain": false,
  "style": {
    "_class": "style",
    "do_objectID": "EA94324E-39B3-4CA3-94B6-340B3C6136EF",
    "endMarkerType": 0,
    "miterLimit": 10,
    "startMarkerType": 0,
    "windingRule": 1
  },
  "symbolID": "8FEB52AC-ED6E-4B62-B42D-8A2D78C1CE3B",
  "verticalSpacing": 0
}