{
  "_class": "symbolInstance",
  "booleanOperation": 0,
  "clippingMaskMode": 0,
  "do_objectID": "803FB0C5-B6C8-403D-8D97-29477E3F2A83",
  "exportOptions": {
    "_class": "exportOptions",
    "do_objectID": "EAE10005-5124-4F92-B472-922A95E78F29",
    "exportFormats": [
    ],
    "includedLayerIds": [
    ],
    "layerOptions": 0,
    "shouldTrim": false
  },
  "frame": {
    "_class": "rect",
    "constrainProportions": false,
    "do_objectID": "13424418-9AC8-4685-9C88-9437997BD3E8",
    "height": 31.0741302713562,
    "width": 34.25493612295998,
    "x": -7.44798755021034,
    "y": -4.682421689847585
  },
  "hasClippingMask": false,
  "horizontalSpacing": 0,
  "isFixedToViewport": false,
  "isFlippedHorizontal": false,
  "isFlippedVertical": false,
  "isLocked": false,
  "isVisible": true,
  "layerListExpandedType": 0,
  "name": "tint",
  "nameIsFixed": true,
  "overrideValues": [
  ],
  "resizingConstraint": 63,
  "resizingType": 0,
  "rotation": 0,
  "scale": 1,
  "shouldBreakMaskChain": false,
  "style": {
    "_class": "style",
    "do_objectID": "5F796714-9EF5-4FC3-80DE-800B962C629A",
    "endMarkerType": 0,
    "miterLimit": 10,
    "startMarkerType": 0,
    "windingRule": 1
  },
  "symbolID": "B2D655A6-143E-435C-A9A8-5BED86F0410F",
  "verticalSpacing": 0
}