{
  "_class": "group",
  "booleanOperation": 0,
  "clippingMaskMode": 0,
  "do_objectID": "8B5A5B50-A7DF-470C-ABFA-551C25D2E24B",
  "exportOptions": {
    "_class": "exportOptions",
    "exportFormats": [
    ],
    "includedLayerIds": [
    ],
    "layerOptions": 0,
    "shouldTrim": false
  },
  "frame": {
    "_class": "rect",
    "constrainProportions": false,
    "height": 179,
    "width": 1060,
    "x": 182,
    "y": 171
  },
  "hasClickThrough": false,
  "hasClippingMask": false,
  "isFixedToViewport": false,
  "isFlippedHorizontal": false,
  "isFlippedVertical": false,
  "isLocked": false,
  "isVisible": true,
  "layerListExpandedType": 0,
  "layers": [
    {
      "class": "text",
      "id": "76A79FFF-B2BD-4BDF-89B7-6772CC8FF193"
    },
    {
      "class": "text",
      "id": "F60ABDCF-2A8C-4E76-BFFC-AFDDB266C6A6"
    },
    {
      "class": "rectangle",
      "id": "C6906102-D0F9-4C9C-B0A3-F67D92E40060"
    },
    {
      "class": "symbolInstance",
      "id": "4E5FE3CD-CFED-4A19-BF13-8F8B488E391B"
    }
  ],
  "name": "Media Drag & Drop Box",
  "nameIsFixed": true,
  "resizingConstraint": 63,
  "resizingType": 0,
  "rotation": 0,
  "shouldBreakMaskChain": false,
  "style": {
    "_class": "style",
    "endMarkerType": 0,
    "miterLimit": 10,
    "startMarkerType": 0,
    "windingRule": 1
  }
}