{
  "_class": "group",
  "booleanOperation": 0,
  "clippingMaskMode": 0,
  "do_objectID": "6607DC0F-BFDF-4F2D-9D91-C3FC9E9EF3EC",
  "exportOptions": {
    "_class": "exportOptions",
    "exportFormats": [
    ],
    "includedLayerIds": [
    ],
    "layerOptions": 0,
    "shouldTrim": false
  },
  "frame": {
    "_class": "rect",
    "constrainProportions": false,
    "height": 85,
    "width": 360,
    "x": 0,
    "y": 111
  },
  "hasClickThrough": false,
  "hasClippingMask": false,
  "isFixedToViewport": false,
  "isFlippedHorizontal": false,
  "isFlippedVertical": false,
  "isLocked": false,
  "isVisible": true,
  "layerListExpandedType": 0,
  "layers": [
    {
      "class": "symbolInstance",
      "id": "C4CE358F-A372-457D-B5A4-6063001871EA"
    },
    {
      "class": "text",
      "id": "39F5F6C5-F755-4C3A-B14A-1C7AFF920BDD"
    },
    {
      "class": "text",
      "id": "E4120C3D-9086-4B73-BA33-20CB0950962B"
    }
  ],
  "name": "slug",
  "nameIsFixed": true,
  "resizingConstraint": 63,
  "resizingType": 0,
  "rotation": 0,
  "shouldBreakMaskChain": false,
  "style": {
    "_class": "style",
    "endMarkerType": 0,
    "miterLimit": 10,
    "startMarkerType": 0,
    "windingRule": 1
  }
}