{
  "_class": "symbolInstance",
  "booleanOperation": 0,
  "clippingMaskMode": 0,
  "do_objectID": "A40B7BA3-4FF0-44AE-BDEC-36781E5120D9",
  "exportOptions": {
    "_class": "exportOptions",
    "do_objectID": "63C1487C-8D74-44D0-BEFB-7308E402EE89",
    "exportFormats": [
    ],
    "includedLayerIds": [
    ],
    "layerOptions": 0,
    "shouldTrim": false
  },
  "frame": {
    "_class": "rect",
    "constrainProportions": false,
    "do_objectID": "24E083EE-381C-4945-86C9-06BC9CB9A28E",
    "height": 18,
    "width": 16,
    "x": 31,
    "y": 25
  },
  "hasClippingMask": false,
  "horizontalSpacing": 0,
  "isFixedToViewport": false,
  "isFlippedHorizontal": false,
  "isFlippedVertical": false,
  "isLocked": false,
  "isVisible": true,
  "layerListExpandedType": 0,
  "name": "dashicon/editor/paragraph",
  "nameIsFixed": false,
  "overrideValues": [
    {
      "_class": "overrideValue",
      "do_objectID": "385D82C9-5E0B-4BB0-BA73-820BE94752B5",
      "overrideName": "98154501-FE53-4F03-A4E2-B5DF2554E08B_symbolID",
      "value": "7DE0ACA5-5CCE-48FF-9A4C-506B432C6A96"
    }
  ],
  "resizingConstraint": 63,
  "resizingType": 0,
  "rotation": 0,
  "scale": 1,
  "shouldBreakMaskChain": false,
  "style": {
    "_class": "style",
    "do_objectID": "936F4E1C-BF9B-4151-9A9B-8F00EFAAE606",
    "endMarkerType": 0,
    "miterLimit": 10,
    "startMarkerType": 0,
    "windingRule": 1
  },
  "symbolID": "941288D6-20CC-43C3-B1D8-E1185B831F2E",
  "verticalSpacing": 0
}