{
  "_class": "group",
  "booleanOperation": 0,
  "clippingMaskMode": 0,
  "do_objectID": "0B1A21CB-43D0-48B5-BD35-362686470A6B",
  "exportOptions": {
    "_class": "exportOptions",
    "exportFormats": [
    ],
    "includedLayerIds": [
    ],
    "layerOptions": 0,
    "shouldTrim": false
  },
  "frame": {
    "_class": "rect",
    "constrainProportions": false,
    "height": 23,
    "width": 126,
    "x": 728,
    "y": 336
  },
  "hasClickThrough": false,
  "hasClippingMask": false,
  "isFixedToViewport": false,
  "isFlippedHorizontal": false,
  "isFlippedVertical": false,
  "isLocked": false,
  "isVisible": true,
  "layerListExpandedType": 1,
  "layers": [
    {
      "class": "oval",
      "id": "BFDD1798-2D43-48AF-BDAF-9ACC79044266"
    },
    {
      "class": "oval",
      "id": "D0EF42DE-D3D0-4E9C-9EBC-D2E8FCEFEE48"
    },
    {
      "class": "oval",
      "id": "F7899C8D-E458-4B05-A3F6-3929B00C7AB7"
    }
  ],
  "name": "Carousel Cirlces",
  "nameIsFixed": true,
  "resizingConstraint": 63,
  "resizingType": 0,
  "rotation": 0,
  "shouldBreakMaskChain": false,
  "style": {
    "_class": "style",
    "endMarkerType": 0,
    "miterLimit": 10,
    "startMarkerType": 0,
    "windingRule": 1
  }
}