{
  "_class": "group",
  "booleanOperation": 0,
  "clippingMaskMode": 0,
  "do_objectID": "AB2B0E08-5621-4800-9700-195E79C49AEF",
  "exportOptions": {
    "_class": "exportOptions",
    "do_objectID": "4082109E-B2C5-463A-AEFD-90116F59A75D",
    "exportFormats": [
    ],
    "includedLayerIds": [
    ],
    "layerOptions": 0,
    "shouldTrim": false
  },
  "frame": {
    "_class": "rect",
    "constrainProportions": false,
    "do_objectID": "54334ADD-B694-497E-98EE-89F1D7DF6958",
    "height": 13,
    "width": 9,
    "x": 6,
    "y": 2
  },
  "hasClickThrough": false,
  "hasClippingMask": false,
  "isFixedToViewport": false,
  "isFlippedHorizontal": false,
  "isFlippedVertical": false,
  "isLocked": false,
  "isVisible": true,
  "layerListExpandedType": 2,
  "layers": [
    {
      "class": "shapeGroup",
      "id": "B611868B-7B8B-41A5-884C-2DC147950349"
    },
    {
      "class": "symbolInstance",
      "id": "A0E42FA5-D636-4B3C-A52D-DAAD12AEB01C"
    }
  ],
  "name": "tint",
  "nameIsFixed": false,
  "resizingConstraint": 63,
  "resizingType": 0,
  "rotation": 0,
  "shouldBreakMaskChain": false,
  "style": {
    "_class": "style",
    "do_objectID": "3528C6AE-EECE-43A5-B567-F8E71BDB3658",
    "endMarkerType": 0,
    "miterLimit": 10,
    "startMarkerType": 0,
    "windingRule": 1
  }
}