{
  "_class": "text",
  "attributedString": {
    "_class": "attributedString",
    "attributes": [
      {
        "_class": "stringAttribute",
        "attributes": {
          "MSAttributedStringColorAttribute": {
            "_class": "color",
            "alpha": 1,
            "blue": 0.3725490196,
            "green": 0.3725490196,
            "red": 0.3725490196
          },
          "MSAttributedStringFontAttribute": {
            "_class": "fontDescriptor",
            "attributes": {
              "name": "OpenSans",
              "size": 13
            }
          },
          "kerning": 0,
          "paragraphStyle": {
            "_class": "paragraphStyle",
            "alignment": 0,
            "allowsDefaultTighteningForTruncation": 0
          }
        },
        "length": 14,
        "location": 0
      }
    ],
    "string": "All Categories"
  },
  "automaticallyDrawOnUnderlyingPath": false,
  "booleanOperation": 0,
  "clippingMaskMode": 0,
  "do_objectID": "78D6D85A-FAE5-4AC1-BF27-EE1AEC03BD6E",
  "dontSynchroniseWithSymbol": false,
  "exportOptions": {
    "_class": "exportOptions",
    "do_objectID": "026F5C9A-5069-4661-9F90-D7AEAC9A7FD9",
    "exportFormats": [
    ],
    "includedLayerIds": [
    ],
    "layerOptions": 0,
    "shouldTrim": false
  },
  "frame": {
    "_class": "rect",
    "constrainProportions": false,
    "do_objectID": "EFE35A7F-6B3D-4F25-8EDC-97313926C0EB",
    "height": 18,
    "width": 93,
    "x": 6,
    "y": 7
  },
  "glyphBounds": "{{0, 0}, {82, 18}}",
  "hasClippingMask": false,
  "isFixedToViewport": false,
  "isFlippedHorizontal": false,
  "isFlippedVertical": false,
  "isLocked": false,
  "isVisible": true,
  "layerListExpandedType": 0,
  "lineSpacingBehaviour": 2,
  "name": "All Categories",
  "nameIsFixed": false,
  "resizingConstraint": 9,
  "resizingType": 1,
  "rotation": 0,
  "sharedStyleID": "47B2D3EC-0454-4015-9787-13ED797071F7",
  "shouldBreakMaskChain": false,
  "style": {
    "_class": "style",
    "do_objectID": "D9E0A820-D467-4AC9-BFB3-88A97840F0F1",
    "endMarkerType": 0,
    "miterLimit": 10,
    "startMarkerType": 0,
    "textStyle": {
      "_class": "textStyle",
      "do_objectID": "70B40BA8-C4A7-4FDB-AFFD-FED0CAFC5A47",
      "encodedAttributes": {
        "MSAttributedStringColorAttribute": {
          "_class": "color",
          "alpha": 1,
          "blue": 0.3725490196,
          "green": 0.3725490196,
          "red": 0.3725490196
        },
        "MSAttributedStringFontAttribute": {
          "_class": "fontDescriptor",
          "attributes": {
            "name": "OpenSans",
            "size": 13
          }
        },
        "kerning": 0,
        "paragraphStyle": {
          "_class": "paragraphStyle",
          "alignment": 0,
          "allowsDefaultTighteningForTruncation": 0
        }
      },
      "verticalAlignment": 0
    },
    "windingRule": 1
  },
  "textBehaviour": 1
}