{
  "_class": "group",
  "booleanOperation": 0,
  "clippingMaskMode": 0,
  "do_objectID": "84E5F940-B898-4D9F-B73D-623B3CACEA3C",
  "exportOptions": {
    "_class": "exportOptions",
    "exportFormats": [
    ],
    "includedLayerIds": [
    ],
    "layerOptions": 0,
    "shouldTrim": false
  },
  "frame": {
    "_class": "rect",
    "constrainProportions": false,
    "height": 92,
    "width": 197,
    "x": 10,
    "y": 89
  },
  "hasClickThrough": false,
  "hasClippingMask": false,
  "isFixedToViewport": false,
  "isFlippedHorizontal": false,
  "isFlippedVertical": false,
  "isLocked": false,
  "isVisible": true,
  "layerListExpandedType": 1,
  "layers": [
    {
      "class": "group",
      "id": "FC102D68-2714-424E-AABD-103DA95CB40F"
    },
    {
      "class": "group",
      "id": "D7322CF0-AE71-419F-B7DA-F4F4DF007809"
    },
    {
      "class": "group",
      "id": "3EB415EC-A2F0-40FC-A3C6-0C239CE21FD9"
    }
  ],
  "name": "publish actions",
  "nameIsFixed": true,
  "resizingConstraint": 33,
  "resizingType": 1,
  "rotation": 0,
  "shouldBreakMaskChain": false,
  "style": {
    "_class": "style",
    "endMarkerType": 0,
    "miterLimit": 10,
    "startMarkerType": 0,
    "windingRule": 1
  }
}