{
  "_class": "shapeGroup",
  "booleanOperation": 0,
  "clippingMaskMode": 0,
  "do_objectID": "C7A25DAE-7521-4F72-85D2-9EF8AD583D96",
  "exportOptions": {
    "_class": "exportOptions",
    "do_objectID": "2CFE4D29-7F0A-4C82-9CA1-7B5B6CD9D45E",
    "exportFormats": [
    ],
    "includedLayerIds": [
    ],
    "layerOptions": 0,
    "shouldTrim": false
  },
  "frame": {
    "_class": "rect",
    "constrainProportions": false,
    "do_objectID": "F58DA475-FE87-49C2-AA7A-888E11B1EFC7",
    "height": 9.891904755189517,
    "width": 9.133525390624982,
    "x": 5.141865234374563,
    "y": 0.4180886460744659
  },
  "hasClickThrough": false,
  "hasClippingMask": false,
  "isFixedToViewport": false,
  "isFlippedHorizontal": false,
  "isFlippedVertical": false,
  "isLocked": false,
  "isVisible": true,
  "layerListExpandedType": 2,
  "layers": [
    {
      "class": "shapePath",
      "id": "1E498BC9-E524-4A57-A86B-7E8978B6042A"
    },
    {
      "class": "shapePath",
      "id": "620509C2-6D38-4875-B76D-EFACD652E9D0"
    }
  ],
  "name": "Shape Copy 2",
  "nameIsFixed": false,
  "resizingConstraint": 63,
  "resizingType": 0,
  "rotation": 0,
  "shouldBreakMaskChain": false,
  "style": {
    "_class": "style",
    "do_objectID": "0CB9911D-2418-4347-A7D8-F3465ECC493E",
    "endMarkerType": 0,
    "fills": [
      {
        "_class": "fill",
        "color": {
          "_class": "color",
          "alpha": 1,
          "blue": 0.4,
          "green": 0.3647058823529412,
          "red": 0.3333333333333333
        },
        "fillType": 0,
        "isEnabled": true,
        "noiseIndex": 0,
        "noiseIntensity": 0,
        "patternFillType": 1,
        "patternTileScale": 1
      }
    ],
    "miterLimit": 10,
    "startMarkerType": 0,
    "windingRule": 1
  },
  "windingRule": 1
}