{
  "_class": "symbolMaster",
  "backgroundColor": {
    "_class": "color",
    "alpha": 1,
    "blue": 1,
    "green": 1,
    "red": 1
  },
  "booleanOperation": 0,
  "changeIdentifier": 616,
  "clippingMaskMode": 0,
  "do_objectID": "A473E79A-03B3-4E62-9687-E2ED81611F14",
  "exportOptions": {
    "_class": "exportOptions",
    "exportFormats": [
    ],
    "includedLayerIds": [
    ],
    "layerOptions": 0,
    "shouldTrim": false
  },
  "frame": {
    "_class": "rect",
    "constrainProportions": false,
    "height": 310,
    "width": 281,
    "x": 11040,
    "y": -1272
  },
  "hasBackgroundColor": false,
  "hasClickThrough": true,
  "hasClippingMask": false,
  "horizontalRulerData": {
    "_class": "rulerData",
    "base": 0,
    "guides": [
    ]
  },
  "includeBackgroundColorInExport": true,
  "includeBackgroundColorInInstance": false,
  "includeInCloudUpload": true,
  "isFixedToViewport": false,
  "isFlippedHorizontal": false,
  "isFlippedVertical": false,
  "isFlowHome": false,
  "isLocked": false,
  "isVisible": true,
  "layerListExpandedType": 0,
  "layers": [
    {
      "class": "group",
      "id": "39154DAB-E1C4-4034-9109-CDE1E7456B46"
    },
    {
      "class": "group",
      "id": "34FB6DCD-54DE-4583-9968-89997B469536"
    },
    {
      "class": "group",
      "id": "D80A2E28-0747-4C77-9CDE-590E2D9AC624"
    },
    {
      "class": "group",
      "id": "4CF42B15-7DAE-4586-94D5-504ABE41F946"
    },
    {
      "class": "group",
      "id": "6143CEBD-4A66-46A8-AEFA-D373A05302A7"
    },
    {
      "class": "group",
      "id": "BE5BBDC5-61D9-4BB1-8BE8-4F6D4B82F043"
    },
    {
      "class": "symbolInstance",
      "id": "3C3D5621-180C-4E70-A38B-70E6D93539F7"
    },
    {
      "class": "symbolInstance",
      "id": "168D93B5-8A8E-47D5-BEFF-0D10669E9467"
    },
    {
      "class": "symbolInstance",
      "id": "6CDA6924-DB8B-430B-8255-505F5437DF36"
    },
    {
      "class": "symbolInstance",
      "id": "D2918819-B9F0-4C3B-8E51-5147FDD24789"
    },
    {
      "class": "text",
      "id": "7ECEA9EB-A95A-4B31-941A-9C6E3EAF8EC8"
    },
    {
      "class": "text",
      "id": "782A9A6A-6913-40C3-A4CF-FF98B2F72F3A"
    },
    {
      "class": "text",
      "id": "E9700708-C9B8-46C9-9BB3-B9C90EF6C2BA"
    },
    {
      "class": "text",
      "id": "496D8514-EF73-45A6-864B-53786260A3C6"
    },
    {
      "class": "text",
      "id": "BBB8B307-79EE-47C5-B603-E1504A375ECF"
    },
    {
      "class": "text",
      "id": "1D5AAF7F-DA3B-43B2-9238-7807124659FD"
    },
    {
      "class": "text",
      "id": "F86970BC-C8B5-4CFA-BE1A-B39D63F8A624"
    },
    {
      "class": "symbolInstance",
      "id": "94AEBF2E-5306-4D54-A80D-F42B88ABE72A"
    },
    {
      "class": "symbolInstance",
      "id": "68F20FF5-48BE-4969-8E1E-182EAB7F78F6"
    },
    {
      "class": "text",
      "id": "8BD13E97-9193-4989-BFFE-CBB98007DEF5"
    },
    {
      "class": "symbolInstance",
      "id": "D1D6ECC5-8DAF-4127-A288-F640AEB5EEB9"
    },
    {
      "class": "rectangle",
      "id": "DE67DBAD-2002-48CE-BF48-E3D792D3E428"
    }
  ],
  "name": "Gutenberg/Core/Publish/Metabox-Saved",
  "nameIsFixed": true,
  "resizesContent": false,
  "resizingConstraint": 63,
  "resizingType": 0,
  "rotation": 0,
  "shouldBreakMaskChain": true,
  "style": {
    "_class": "style",
    "endMarkerType": 0,
    "miterLimit": 10,
    "startMarkerType": 0,
    "windingRule": 1
  },
  "symbolID": "0B942806-B13F-497F-852A-8947C754FA21",
  "verticalRulerData": {
    "_class": "rulerData",
    "base": 0,
    "guides": [
    ]
  }
}