{
  "_class": "symbolInstance",
  "booleanOperation": 0,
  "clippingMaskMode": 0,
  "do_objectID": "321ECF74-7616-4F40-BA1F-F5D8FBE8BD41",
  "exportOptions": {
    "_class": "exportOptions",
    "do_objectID": "9AE6940A-B58A-40BF-AF4E-CE2632253ACA",
    "exportFormats": [
    ],
    "includedLayerIds": [
    ],
    "layerOptions": 0,
    "shouldTrim": false
  },
  "frame": {
    "_class": "rect",
    "constrainProportions": false,
    "do_objectID": "A3990AA5-B598-45E5-B356-D86EC79BBDA8",
    "height": 21,
    "width": 21,
    "x": 0,
    "y": 0
  },
  "hasClippingMask": false,
  "horizontalSpacing": 0,
  "isFixedToViewport": false,
  "isFlippedHorizontal": false,
  "isFlippedVertical": false,
  "isLocked": false,
  "isVisible": true,
  "layerListExpandedType": 0,
  "name": "tint",
  "nameIsFixed": true,
  "overrideValues": [
  ],
  "resizingConstraint": 63,
  "resizingType": 0,
  "rotation": 0,
  "scale": 1,
  "shouldBreakMaskChain": false,
  "style": {
    "_class": "style",
    "do_objectID": "49B0CF53-7B13-4623-B847-10AD218C5260",
    "endMarkerType": 0,
    "miterLimit": 10,
    "startMarkerType": 0,
    "windingRule": 1
  },
  "symbolID": "8FEB52AC-ED6E-4B62-B42D-8A2D78C1CE3B",
  "verticalSpacing": 0
}