{
  "_class": "shapePath",
  "booleanOperation": -1,
  "clippingMaskMode": 0,
  "do_objectID": "0586CB4C-BD66-4CBA-89F2-C5C285831A95",
  "edited": true,
  "exportOptions": {
    "_class": "exportOptions",
    "do_objectID": "F1D81264-2B15-4A72-BEF4-7183D7700A4D",
    "exportFormats": [
    ],
    "includedLayerIds": [
    ],
    "layerOptions": 0,
    "shouldTrim": false
  },
  "frame": {
    "_class": "rect",
    "constrainProportions": false,
    "do_objectID": "D65A922E-7063-4B02-9239-C8EF70A62695",
    "height": 13.46,
    "width": 14.00000000000001,
    "x": 0,
    "y": 0.5399999999999636
  },
  "hasClippingMask": false,
  "isClosed": true,
  "isFixedToViewport": false,
  "isFlippedHorizontal": false,
  "isFlippedVertical": false,
  "isLocked": false,
  "isVisible": true,
  "layerListExpandedType": 0,
  "name": "Shape",
  "nameIsFixed": false,
  "pointRadiusBehaviour": 0,
  "points": [
    {
      "_class": "curvePoint",
      "cornerRadius": 0,
      "curveFrom": "{0.59071428571428575, 0.13818722139673106}",
      "curveMode": 4,
      "curveTo": "{0.50000000000000011, 0.13818722139673106}",
      "hasCurveFrom": true,
      "hasCurveTo": false,
      "point": "{0.50000000000000011, 0.13818722139673106}"
    },
    {
      "_class": "curvePoint",
      "cornerRadius": 0,
      "curveFrom": "{0.75500000000000012, 0.27117384843982167}",
      "curveMode": 2,
      "curveTo": "{0.66000000000000003, 0.16493313521545322}",
      "hasCurveFrom": true,
      "hasCurveTo": true,
      "point": "{0.70785714285714285, 0.21842496285289748}"
    },
    {
      "_class": "curvePoint",
      "cornerRadius": 0,
      "curveFrom": "{0.77928571428571447, 0.54606240713224363}",
      "curveMode": 2,
      "curveTo": "{0.77928571428571447, 0.34918276374442792}",
      "hasCurveFrom": true,
      "hasCurveTo": true,
      "point": "{0.77928571428571447, 0.45096582466567597}"
    },
    {
      "_class": "curvePoint",
      "cornerRadius": 0,
      "curveFrom": "{0.69642857142857151, 0.76002971768202077}",
      "curveMode": 4,
      "curveTo": "{0.76285714285714301, 0.62704309063893016}",
      "hasCurveFrom": true,
      "hasCurveTo": true,
      "point": "{0.73000000000000009, 0.69390787518573549}"
    },
    {
      "_class": "curvePoint",
      "cornerRadius": 0,
      "curveFrom": "{0.57142857142857151, 0.85141158989598809}",
      "curveMode": 4,
      "curveTo": "{0.63928571428571446, 0.80683506686478446}",
      "hasCurveFrom": false,
      "hasCurveTo": true,
      "point": "{0.57142857142857151, 0.85141158989598809}"
    },
    {
      "_class": "curvePoint",
      "cornerRadius": 0,
      "curveFrom": "{0.57142857142857151, 1}",
      "curveMode": 1,
      "curveTo": "{0.57142857142857151, 1}",
      "hasCurveFrom": false,
      "hasCurveTo": false,
      "point": "{0.57142857142857151, 1}"
    },
    {
      "_class": "curvePoint",
      "cornerRadius": 0,
      "curveFrom": "{1.0000000000000002, 1}",
      "curveMode": 1,
      "curveTo": "{1.0000000000000002, 1}",
      "hasCurveFrom": false,
      "hasCurveTo": false,
      "point": "{1.0000000000000002, 1}"
    },
    {
      "_class": "curvePoint",
      "cornerRadius": 0,
      "curveFrom": "{1.0000000000000002, 0.85141158989598809}",
      "curveMode": 1,
      "curveTo": "{1.0000000000000002, 0.85141158989598809}",
      "hasCurveFrom": false,
      "hasCurveTo": false,
      "point": "{1.0000000000000002, 0.85141158989598809}"
    },
    {
      "_class": "curvePoint",
      "cornerRadius": 0,
      "curveFrom": "{0.80214285714285727, 0.80386329866270423}",
      "curveMode": 4,
      "curveTo": "{0.73642857142857154, 0.85141158989598809}",
      "hasCurveFrom": true,
      "hasCurveTo": false,
      "point": "{0.73642857142857154, 0.85141158989598809}"
    },
    {
      "_class": "curvePoint",
      "cornerRadius": 0,
      "curveFrom": "{0.92285714285714293, 0.60252600297176828}",
      "curveMode": 4,
      "curveTo": "{0.8521428571428572, 0.75185735512630014}",
      "hasCurveFrom": true,
      "hasCurveTo": true,
      "point": "{0.88785714285714301, 0.67756315007429424}"
    },
    {
      "_class": "curvePoint",
      "cornerRadius": 0,
      "curveFrom": "{0.94071428571428573, 0.29643387815750372}",
      "curveMode": 3,
      "curveTo": "{0.94071428571428573, 0.51931649331352159}",
      "hasCurveFrom": true,
      "hasCurveTo": true,
      "point": "{0.94071428571428573, 0.42867756315007427}"
    },
    {
      "_class": "curvePoint",
      "cornerRadius": 0,
      "curveFrom": "{0.74428571428571422, 0.038632986627043127}",
      "curveMode": 2,
      "curveTo": "{0.90142857142857136, 0.19167904903417537}",
      "hasCurveFrom": true,
      "hasCurveTo": true,
      "point": "{0.82285714285714284, 0.11515601783060926}"
    },
    {
      "_class": "curvePoint",
      "cornerRadius": 0,
      "curveFrom": "{0.36285714285714282, 6.5986509635967687e-17}",
      "curveMode": 2,
      "curveTo": "{0.63714285714285701, 6.5986509635967687e-17}",
      "hasCurveFrom": true,
      "hasCurveTo": true,
      "point": "{0.49999999999999994, 6.5986509635967687e-17}"
    },
    {
      "_class": "curvePoint",
      "cornerRadius": 0,
      "curveFrom": "{0.098571428571428574, 0.19390787518573557}",
      "curveMode": 2,
      "curveTo": "{0.255, 0.039375928677563232}",
      "hasCurveFrom": true,
      "hasCurveTo": true,
      "point": "{0.17714285714285713, 0.11664190193164942}"
    },
    {
      "_class": "curvePoint",
      "cornerRadius": 0,
      "curveFrom": "{0.059285714285714268, 0.51857355126300175}",
      "curveMode": 3,
      "curveTo": "{0.059285714285714268, 0.29791976225854383}",
      "hasCurveFrom": true,
      "hasCurveTo": true,
      "point": "{0.059285714285714268, 0.42867756315007444}"
    },
    {
      "_class": "curvePoint",
      "cornerRadius": 0,
      "curveFrom": "{0.14571428571428574, 0.7511144130757802}",
      "curveMode": 2,
      "curveTo": "{0.076428571428571387, 0.60029717682020822}",
      "hasCurveFrom": true,
      "hasCurveTo": true,
      "point": "{0.1114285714285714, 0.67607726597325424}"
    },
    {
      "_class": "curvePoint",
      "cornerRadius": 0,
      "curveFrom": "{0.2614285714285714, 0.8514115898959882}",
      "curveMode": 4,
      "curveTo": "{0.1964285714285714, 0.80312035661218439}",
      "hasCurveFrom": false,
      "hasCurveTo": true,
      "point": "{0.2614285714285714, 0.8514115898959882}"
    },
    {
      "_class": "curvePoint",
      "cornerRadius": 0,
      "curveFrom": "{-6.3441315692866072e-17, 0.8514115898959882}",
      "curveMode": 1,
      "curveTo": "{-6.3441315692866072e-17, 0.8514115898959882}",
      "hasCurveFrom": false,
      "hasCurveTo": false,
      "point": "{-6.3441315692866072e-17, 0.8514115898959882}"
    },
    {
      "_class": "curvePoint",
      "cornerRadius": 0,
      "curveFrom": "{-6.3441315692866072e-17, 1}",
      "curveMode": 1,
      "curveTo": "{-6.3441315692866072e-17, 1}",
      "hasCurveFrom": false,
      "hasCurveTo": false,
      "point": "{-6.3441315692866072e-17, 1}"
    },
    {
      "_class": "curvePoint",
      "cornerRadius": 0,
      "curveFrom": "{0.42857142857142855, 1}",
      "curveMode": 1,
      "curveTo": "{0.42857142857142855, 1}",
      "hasCurveFrom": false,
      "hasCurveTo": false,
      "point": "{0.42857142857142855, 1}"
    },
    {
      "_class": "curvePoint",
      "cornerRadius": 0,
      "curveFrom": "{0.35857142857142849, 0.80386329866270423}",
      "curveMode": 4,
      "curveTo": "{0.42857142857142855, 0.85141158989598809}",
      "hasCurveFrom": true,
      "hasCurveTo": false,
      "point": "{0.42857142857142855, 0.85141158989598809}"
    },
    {
      "_class": "curvePoint",
      "cornerRadius": 0,
      "curveFrom": "{0.23642857142857138, 0.62407132243684993}",
      "curveMode": 2,
      "curveTo": "{0.29999999999999999, 0.75631500742942059}",
      "hasCurveFrom": true,
      "hasCurveTo": true,
      "point": "{0.26857142857142852, 0.69019316493313521}"
    },
    {
      "_class": "curvePoint",
      "cornerRadius": 0,
      "curveFrom": "{0.22071428571428567, 0.3491827637444278}",
      "curveMode": 2,
      "curveTo": "{0.22071428571428567, 0.54457652303120363}",
      "hasCurveFrom": true,
      "hasCurveTo": true,
      "point": "{0.22071428571428567, 0.45096582466567597}"
    },
    {
      "_class": "curvePoint",
      "cornerRadius": 0,
      "curveFrom": "{0.33928571428571425, 0.16493313521545316}",
      "curveMode": 2,
      "curveTo": "{0.24428571428571424, 0.27191679049034168}",
      "hasCurveFrom": true,
      "hasCurveTo": true,
      "point": "{0.29214285714285709, 0.21842496285289742}"
    },
    {
      "_class": "curvePoint",
      "cornerRadius": 0,
      "curveFrom": "{0.49999999999999994, 0.13818722139673098}",
      "curveMode": 4,
      "curveTo": "{0.40857142857142864, 0.13818722139673098}",
      "hasCurveFrom": false,
      "hasCurveTo": true,
      "point": "{0.49999999999999994, 0.13818722139673098}"
    }
  ],
  "resizingConstraint": 63,
  "resizingType": 0,
  "rotation": 0,
  "shouldBreakMaskChain": false,
  "style": {
    "_class": "style",
    "do_objectID": "D863AC2B-A4E3-42A3-AF15-545F9DBB5B8B",
    "endMarkerType": 0,
    "fills": [
      {
        "_class": "fill",
        "color": {
          "_class": "color",
          "alpha": 1,
          "blue": 0.4,
          "green": 0.3647058823529412,
          "red": 0.3333333333333333
        },
        "fillType": 0,
        "isEnabled": true,
        "noiseIndex": 0,
        "noiseIntensity": 0,
        "patternFillType": 1,
        "patternTileScale": 1
      }
    ],
    "miterLimit": 10,
    "startMarkerType": 0,
    "windingRule": 1
  }
}