{
  "_class": "shapeGroup",
  "booleanOperation": 0,
  "clippingMaskMode": 0,
  "do_objectID": "DD60159D-F29B-4A44-A8C9-2F1F6DD78775",
  "exportOptions": {
    "_class": "exportOptions",
    "exportFormats": [
    ],
    "includedLayerIds": [
    ],
    "layerOptions": 0,
    "shouldTrim": false
  },
  "frame": {
    "_class": "rect",
    "constrainProportions": false,
    "height": 14,
    "width": 14,
    "x": 0,
    "y": 0
  },
  "hasClickThrough": false,
  "hasClippingMask": false,
  "isFixedToViewport": false,
  "isFlippedHorizontal": false,
  "isFlippedVertical": false,
  "isLocked": false,
  "isVisible": true,
  "layerListExpandedType": 0,
  "layers": [
    {
      "class": "shapePath",
      "id": "5DFE36F5-F99B-44C3-BF17-362E4DC70F35"
    },
    {
      "class": "shapePath",
      "id": "44DB2894-74E2-4260-8DED-DBF5E9A91B80"
    },
    {
      "class": "shapePath",
      "id": "0F3295C4-990D-4D96-96D5-473D5CA5BAA4"
    },
    {
      "class": "shapePath",
      "id": "73340E3D-643F-4B20-94A9-9440483C12C2"
    },
    {
      "class": "shapePath",
      "id": "0049C12D-CD50-4CDB-BB8E-04C1E8EF6DC5"
    }
  ],
  "name": "Shape",
  "nameIsFixed": false,
  "resizingConstraint": 63,
  "resizingType": 0,
  "rotation": 0,
  "shouldBreakMaskChain": false,
  "style": {
    "_class": "style",
    "endMarkerType": 0,
    "fills": [
      {
        "_class": "fill",
        "color": {
          "_class": "color",
          "alpha": 1,
          "blue": 0.4,
          "green": 0.3647058823529412,
          "red": 0.3333333333333333
        },
        "fillType": 0,
        "isEnabled": true,
        "noiseIndex": 0,
        "noiseIntensity": 0,
        "patternFillType": 1,
        "patternTileScale": 1
      }
    ],
    "miterLimit": 10,
    "startMarkerType": 0,
    "windingRule": 1
  },
  "windingRule": 1
}